README.md
setup.cfg
setup.py
disapi/disapi.py
disapi/main.py
disapi.egg-info/PKG-INFO
disapi.egg-info/SOURCES.txt
disapi.egg-info/dependency_links.txt
disapi.egg-info/top_level.txt